kit4dl/__init__.py
kit4dl/_version.py
kit4dl/context.py
kit4dl/formatting.py
kit4dl/io.py
kit4dl/kit4dl_types.py
kit4dl/metric.py
kit4dl/mixins.py
kit4dl/stages.py
kit4dl/utils.py
kit4dl/cli/__init__.py
kit4dl/cli/app.py
kit4dl/cli/_templates/project/conf.toml
kit4dl/cli/_templates/project/datamodule.py
kit4dl/cli/_templates/project/model.py
kit4dl/nn/__init__.py
kit4dl/nn/base.py
kit4dl/nn/callbacks.py
kit4dl/nn/confmodels.py
kit4dl/nn/dataset.py
kit4dl/nn/trainer.py
kit4dl/nn/validators.py
tests/__init__.py
tests/dummy_module.py
tests/dummy_module2.py
tests/fixtures.py
tests/test_context.py
tests/test_datamodule.py
tests/test_formatting.py
tests/test_init.py
tests/test_io.py
tests/test_metrics.py
tests/test_mixins.py
tests/utils.py
tests/cli/__init__.py
tests/cli/test_app.py
tests/nn/__init__.py
tests/nn/test_base.py
tests/nn/test_confmodels.py
tests/nn/test_trainer.py
tests/nn/test_validators.py
tests/resources/dataset.py
tests/resources/model.py
tests/resources/test_file.toml
kit4dl-2024.5b2.dist-info/LICENSE
kit4dl-2024.5b2.dist-info/METADATA
kit4dl-2024.5b2.dist-info/WHEEL
kit4dl-2024.5b2.dist-info/entry_points.txt
kit4dl-2024.5b2.dist-info/top_level.txt
kit4dl-2024.5b2.dist-info/RECORD
