Metadata-Version: 2.1
Name: kit4dl
Version: 2024.5b2
Summary: Kit4DL - A quick way to start with machine and deep learning
Author: Jakub Walczak, Marco Mancini, Mirko Stojiljkovic, Shahbaz Alvi
License: MIT License
Project-URL: Homepage, https://opengeokube.github.io/kit4dl/
Project-URL: Documentation, https://opengeokube.github.io/kit4dl/
Project-URL: Source Code, https://github.com/opengeokube/kit4dl
Project-URL: Bug Tracker, https://github.com/opengeokube/kit4dl/issues
Keywords: deep learning,training pipeline
Classifier: Development Status :: 4 - Beta
Classifier: Operating System :: OS Independent
Classifier: License :: OSI Approved :: MIT License
Classifier: Programming Language :: Python
Classifier: Programming Language :: Python :: 3
Classifier: Programming Language :: Python :: 3 :: Only
Classifier: Programming Language :: Python :: 3.10
Classifier: Programming Language :: Python :: 3.11
Classifier: Intended Audience :: Developers
Classifier: Intended Audience :: Education
Classifier: Intended Audience :: End Users/Desktop
Classifier: Topic :: Scientific/Engineering :: Artificial Intelligence
Classifier: Topic :: Software Development :: Libraries :: Python Modules
Classifier: Topic :: Software Development :: Libraries :: Application Frameworks
Classifier: Topic :: Software Development :: Libraries
Requires-Python: >=3.10
License-File: LICENSE
Requires-Dist: lightning >=2.2.4
Requires-Dist: torch >=2.1.0
Requires-Dist: torchmetrics >=1.1.0
Requires-Dist: numpy <=1.25.3,>=1.17.2
Requires-Dist: pydantic >2.4.0
Requires-Dist: scikit-learn
Requires-Dist: colormath
Requires-Dist: tqdm <4.67.0,>=4.57.0
Requires-Dist: typing-extensions >=4.8.0
Requires-Dist: Jinja2 <3.2.0
Requires-Dist: typer[all]
Requires-Dist: toml ; python_version < "3.11"
